x_all_modules/__init__.py
x_all_modules-0.1.1.dist-info/METADATA
x_all_modules-0.1.1.dist-info/WHEEL
x_all_modules-0.1.1.dist-info/licenses/LICENSE
x_all_modules-0.1.1.dist-info/RECORD
