Metadata-Version: 2.4
Name: x_all_modules
Version: 0.1.1
Summary: It is a module which, if you import then you won't need to import any other module for any purpose...
Author-email: Ashutosh Dwivedi <iasashutosh17@gmail.com>
License: Creative Commons Attribution-NonCommercial 4.0 International Public License
License-File: LICENSE
Classifier: License :: OSI Approved :: MIT License
Classifier: Operating System :: OS Independent
Classifier: Programming Language :: Python :: 3
Requires-Python: >=3.7
